yahooFinanceWrapper/__init__.py
yahooFinanceWrapper/__main__.py
yahoofinancewrapper-0.0.5.dist-info/METADATA
yahoofinancewrapper-0.0.5.dist-info/WHEEL
yahoofinancewrapper-0.0.5.dist-info/licenses/LICENSE
yahoofinancewrapper-0.0.5.dist-info/RECORD
